chessan/__init__.py
chessan-0.1.0.dist-info/LICENSE
chessan-0.1.0.dist-info/METADATA
chessan-0.1.0.dist-info/WHEEL
chessan-0.1.0.dist-info/RECORD
